element_electrode_localization/__init__.py
element_electrode_localization/coordinate_framework.py
element_electrode_localization/electrode_localization.py
element_electrode_localization/version.py
element_electrode_localization-0.1.4.dist-info/LICENSE
element_electrode_localization-0.1.4.dist-info/METADATA
element_electrode_localization-0.1.4.dist-info/WHEEL
element_electrode_localization-0.1.4.dist-info/top_level.txt
element_electrode_localization-0.1.4.dist-info/RECORD
