Metadata-Version: 2.1
Name: element-electrode-localization
Version: 0.1.4
Summary: Electrode localization DataJoint element
Home-page: https://github.com/datajoint/element-electrode-localization
Author: DataJoint
Author-email: info@datajoint.com
License: MIT
Keywords: neuroscience electrode science datajoint
Platform: UNKNOWN
License-File: LICENSE
Requires-Dist: datajoint (>=0.13)
Requires-Dist: element-interface (>=0.3.0)
Requires-Dist: pynrrd
